fidap/__init__.py
fidap/fidap.py
fidap/settings.py
fidap-0.0.16.dist-info/LICENSE.txt
fidap-0.0.16.dist-info/METADATA
fidap-0.0.16.dist-info/WHEEL
fidap-0.0.16.dist-info/top_level.txt
fidap-0.0.16.dist-info/RECORD
