Metadata-Version: 2.1
Name: fidap
Version: 0.0.16
Summary: Access clean external data easily.
Home-page: https://github.com/fidapco/fidap-python
Author: Ashish Singal
Author-email: ashish.singal1@gmail.com
License: MIT
Download-URL: https://pypi.org/project/fidap/
Keywords: API,data,financial,economic,fidap
Platform: UNKNOWN
Classifier: Programming Language :: Python :: 3
Classifier: License :: OSI Approved :: MIT License
Classifier: Operating System :: OS Independent
Requires-Python: >=3.6
License-File: LICENSE.txt
Requires-Dist: pandas (>=0.14)
Requires-Dist: numpy (>=1.8)
Requires-Dist: requests (>=2.7.0)
Requires-Dist: python-dotenv (>=0.15.0)
Requires-Dist: delta-sharing
